afiz_speech_text/__init__.py
afiz_speech_text/_modidx.py
afiz_speech_text/assemblyai.py
afiz_speech_text-0.0.3.dist-info/LICENSE
afiz_speech_text-0.0.3.dist-info/METADATA
afiz_speech_text-0.0.3.dist-info/WHEEL
afiz_speech_text-0.0.3.dist-info/entry_points.txt
afiz_speech_text-0.0.3.dist-info/top_level.txt
afiz_speech_text-0.0.3.dist-info/RECORD
