Metadata-Version: 2.1
Name: afiz-speech-text
Version: 0.0.3
Summary: Transcribe and understand your audio/video files super fast.
Home-page: https://github.com/afizs/afiz-speech-text
Author: Afiz
Author-email: itsafiz@gmail.com
License: Apache Software License 2.0
Keywords: nbdev jupyter notebook python
Classifier: Development Status :: 4 - Beta
Classifier: Intended Audience :: Developers
Classifier: Natural Language :: English
Classifier: Programming Language :: Python :: 3.7
Classifier: Programming Language :: Python :: 3.8
Classifier: Programming Language :: Python :: 3.9
Classifier: Programming Language :: Python :: 3.10
Classifier: License :: OSI Approved :: Apache Software License
Requires-Python: >=3.7
License-File: LICENSE
Requires-Dist: requests
Requires-Dist: fastcore
Provides-Extra: dev
